proxy_meshx-2.3.0.dist-info/licenses/LICENSE
proxyhunter/__init__.py
proxyhunter/__main__.py
proxyhunter/core.py
proxyhunter/i18n.py
proxyhunter/proxy_session.py
proxyhunter/web_app.py
proxyhunter/i18n/__init__.py
proxyhunter/i18n/en.json
proxyhunter/i18n/ja.json
proxyhunter/i18n/zh.json
proxyhunter/public/__init__.py
proxyhunter/public/index.html
proxyhunter/public/traffic.html
proxy_meshx-2.3.0.dist-info/METADATA
proxy_meshx-2.3.0.dist-info/WHEEL
proxy_meshx-2.3.0.dist-info/entry_points.txt
proxy_meshx-2.3.0.dist-info/top_level.txt
proxy_meshx-2.3.0.dist-info/RECORD
