Metadata-Version: 2.4
Name: proxy-meshx
Version: 2.3.0
Summary: Professional proxy fetching and validation tool for red team operations and web scraping
Home-page: https://github.com/sheng1111/Proxy-Hunter
Author: sheng1111
Author-email: sheng1111 <ysl58200@gmail.com>
License-Expression: MIT
Project-URL: Homepage, https://github.com/sheng1111/Proxy-Hunter
Project-URL: Repository, https://github.com/sheng1111/Proxy-Hunter
Project-URL: Documentation, https://github.com/sheng1111/Proxy-Hunter/blob/main/README.md
Project-URL: Bug Reports, https://github.com/sheng1111/Proxy-Hunter/issues
Keywords: proxy,scraping,red-team,security,networking,validation,anonymity
Classifier: Development Status :: 4 - Beta
Classifier: Intended Audience :: Developers
Classifier: Intended Audience :: Information Technology
Classifier: Operating System :: OS Independent
Classifier: Programming Language :: Python :: 3
Classifier: Programming Language :: Python :: 3.8
Classifier: Programming Language :: Python :: 3.9
Classifier: Programming Language :: Python :: 3.10
Classifier: Programming Language :: Python :: 3.11
Classifier: Programming Language :: Python :: 3.12
Classifier: Topic :: Internet :: Proxy Servers
Classifier: Topic :: Internet :: WWW/HTTP
Classifier: Topic :: Security
Classifier: Topic :: Software Development :: Libraries :: Python Modules
Classifier: Topic :: System :: Networking
Requires-Python: >=3.8
License-File: LICENSE
Requires-Dist: requests>=2.31.0
Requires-Dist: flask>=3.1.1
Requires-Dist: urllib3>=2.2.0
Requires-Dist: certifi>=2024.0.0
Requires-Dist: flask-socketio>=5.3.0
Requires-Dist: python-socketio>=5.10.0
Requires-Dist: eventlet>=0.33.0
Requires-Dist: Jinja2>=3.1.0
Provides-Extra: dev
Requires-Dist: pytest>=8.0.0; extra == "dev"
Requires-Dist: pytest-cov>=4.0.0; extra == "dev"
Requires-Dist: black>=23.0.0; extra == "dev"
Requires-Dist: flake8>=6.0.0; extra == "dev"
Requires-Dist: mypy>=1.0.0; extra == "dev"
Provides-Extra: web
Requires-Dist: gunicorn>=21.0.0; extra == "web"
Requires-Dist: waitress>=3.0.0; extra == "web"
Provides-Extra: full
Requires-Dist: plotly>=5.18.0; extra == "full"
Requires-Dist: pandas>=2.1.0; extra == "full"
Requires-Dist: sqlalchemy>=2.0.0; extra == "full"
Dynamic: author
Dynamic: home-page
Dynamic: license-file
Dynamic: requires-python
